dotaservice/__init__.py
dotaservice/__main__.py
dotaservice/dotaservice.py
dotaservice/lua/action_processor.lua
dotaservice/lua/bot_generic.lua
dotaservice/lua/config.lua
dotaservice/lua/hero_selection.lua
dotaservice/lua/pprint.lua
dotaservice/lua/uuid.lua
dotaservice/protos/DotaService_grpc.py
dotaservice/protos/DotaService_pb2.py
dotaservice/protos/DotaService_pb2_grpc.py
dotaservice/protos/__init__.py
dotaservice/protos/dota_gcmessages_common_bot_script_pb2.py
dotaservice/protos/dota_gcmessages_common_bot_script_pb2_grpc.py
dotaservice/protos/dota_shared_enums_pb2.py
dotaservice/protos/dota_shared_enums_pb2_grpc.py
dotaservice-0.3.9.dist-info/LICENSE
dotaservice-0.3.9.dist-info/METADATA
dotaservice-0.3.9.dist-info/WHEEL
dotaservice-0.3.9.dist-info/top_level.txt
dotaservice-0.3.9.dist-info/RECORD
