Metadata-Version: 2.1
Name: dotaservice
Version: 0.3.9
Summary: DotaService is a service to play Dota 2 through gRPC
Home-page: https://github.com/TimZaman/DotaService
Author: Tim Zaman
Author-email: timbobel@gmail.com
License: UNKNOWN
Platform: UNKNOWN
Classifier: Intended Audience :: Education
Classifier: Intended Audience :: Science/Research
Classifier: License :: Freeware
Classifier: License :: Other/Proprietary License
Classifier: Operating System :: MacOS
Classifier: Operating System :: Unix
Classifier: Programming Language :: Python :: 3 :: Only
Classifier: Programming Language :: Python :: 3.7
Classifier: Topic :: Scientific/Engineering :: Artificial Intelligence
Classifier: Topic :: Scientific/Engineering
Classifier: Topic :: Software Development :: Libraries :: Python Modules
Classifier: Topic :: Software Development :: Libraries
Classifier: Topic :: Software Development
Requires-Python: >=3.7
Requires-Dist: grpclib
Requires-Dist: protobuf
Provides-Extra: dev
Requires-Dist: grpcio-tools ; extra == 'dev'
